cepack/__init__.py
cepack/main.py
cepack/utility.py
test/__init__.py
test/test_ci.py
test/test_utility.py
test/utility/__init__.py
test/utility/env_manage.py
cepack-0.0.6.dist-info/LICENSE
cepack-0.0.6.dist-info/METADATA
cepack-0.0.6.dist-info/WHEEL
cepack-0.0.6.dist-info/entry_points.txt
cepack-0.0.6.dist-info/top_level.txt
cepack-0.0.6.dist-info/RECORD
