Metadata-Version: 2.1
Name: cepack
Version: 0.0.6
Summary: embedded pack manage
Author-email: paopaozhi <paopaozhi@hotmail.com>
Project-URL: Homepage, https://github.com/paopaozhi/cepack
Project-URL: Bug Tracker, https://github.com/paopaozhi/cepack/issues
Classifier: Programming Language :: Python :: 3.9
Classifier: License :: OSI Approved :: GNU General Public License v3 (GPLv3)
Classifier: Operating System :: OS Independent
Requires-Python: >=3.9
License-File: LICENSE
Requires-Dist: typer
Requires-Dist: toml
Requires-Dist: requests
